DropTheBeat-1.0.dist-info/DESCRIPTION.rst
DropTheBeat-1.0.dist-info/METADATA
DropTheBeat-1.0.dist-info/RECORD
DropTheBeat-1.0.dist-info/WHEEL
DropTheBeat-1.0.dist-info/entry_points.txt
DropTheBeat-1.0.dist-info/metadata.json
DropTheBeat-1.0.dist-info/top_level.txt
dtb/__init__.py
dtb/cli.py
dtb/common.py
dtb/gui.py
dtb/settings.py
dtb/share.py
dtb/song.py
dtb/user.py
dtb/tests/__init__.py
dtb/tests/test_cli.py
dtb/tests/test_gui.py
dtb/tests/test_share.py
dtb/tests/test_song.py
dtb/tests/test_user.py
tests/__init__.py
