Metadata-Version: 2.0
Name: DropTheBeat
Version: 1.0
Summary: Music sharing using Dropbox.
Home-page: https://github.com/jacebrowning/dropthebeat
Author: Jace Browning
Author-email: jacebrowning@gmail.com
License: MIT
Platform: UNKNOWN
Classifier: Development Status :: 5 - Production/Stable
Classifier: Environment :: Console
Classifier: Environment :: MacOS X
Classifier: Environment :: Win32 (MS Windows)
Classifier: Environment :: X11 Applications
Classifier: Intended Audience :: End Users/Desktop
Classifier: License :: OSI Approved :: MIT License
Classifier: Natural Language :: English
Classifier: Operating System :: OS Independent
Classifier: Programming Language :: Python :: 3
Classifier: Programming Language :: Python :: 3.3
Classifier: Programming Language :: Python :: 3.4
Classifier: Programming Language :: Python :: 3.5
Classifier: Topic :: Communications :: File Sharing
Classifier: Topic :: Multimedia :: Sound/Audio
Requires-Dist: PyYAML (~=3.10)
